macro/__init__.py
macro/clipboard.py
macro/keyboard.py
macro/mouse.py
macro/utils.py
macro/window.py
easymacro-0.0.3.dist-info/METADATA
easymacro-0.0.3.dist-info/WHEEL
easymacro-0.0.3.dist-info/top_level.txt
easymacro-0.0.3.dist-info/RECORD
