Metadata-Version: 2.1
Name: easymacro
Version: 0.0.3
Summary: Easily make macros in Python!
Author: Wurgo, Languste27
Author-email: <wurgoalt@gmail.com>
Keywords: python,macro,windows,mouse,keyboard,input
Requires-Dist: pywin32
